project/__init__.py
project/_version.py
project/output.pdb
project/project.py
project/data/README.md
project/data/input.pdb
project/data/look_and_say.dat
project/tests/__init__.py
project/tests/test_project.py
projectwithanewname-0.0.3.dist-info/LICENSE
projectwithanewname-0.0.3.dist-info/METADATA
projectwithanewname-0.0.3.dist-info/WHEEL
projectwithanewname-0.0.3.dist-info/top_level.txt
projectwithanewname-0.0.3.dist-info/RECORD
