Metadata-Version: 2.1
Name: projectwithanewname
Version: 0.0.3
Summary: UNKNOWN
Home-page: https://github.com/cabb99/cookiecutter-cms
Author: cookie monster
Author-email: cookiemonster@trash.can
License: MIT
Platform: UNKNOWN
